{"is_source_file": true, "format": "Dart", "description": "This file defines a Dart class NotificationItem representing a notification with properties like id, userId, message, and read status. It includes methods for JSON serialization and deserialization.", "external_files": ["package:flutter/foundation.dart"], "external_methods": [], "published": ["NotificationItem"], "classes": [{"name": "NotificationItem", "description": "An immutable class representing a notification item with serialization to and from JSON."}], "methods": [{"name": "fromJson", "description": "Creates a NotificationItem instance from a JSON map."}, {"name": "toJson", "description": "Converts the NotificationItem instance into a JSON map."}], "calls": ["NotificationItem.fromJson", "NotificationItem.toJson"], "search-terms": ["NotificationItem", "notification Dart class", "json serialization Dart", "immutable class Flutter"], "state": 2, "file_id": 127, "knowledge_revision": 277, "git_revision": "", "hash": "ca4a5f26777389e9e397cf28f8f89fc5", "format-version": 4, "code-base-name": "MobileApplication", "filename": "MobileApplication/lib/models/notification_item.dart", "revision_history": [{"277": ""}]}