{"is_source_file": true, "format": "JavaScript (React JSX)", "description": "This file defines a React component 'Loyalty' that manages and displays a list of loyalty accounts, allowing editing of points and tier information. It fetches data from an API, supports updating entries, and renders a table UI.", "external_files": ["../api/client", "../api/endpoints", "../components/NavBar"], "external_methods": ["api.get", "api.put", "withId"], "published": ["Loyalty"], "classes": [], "methods": [{"name": "load", "description": "Fetches loyalty account data from the API and updates the state."}, {"name": "startEdit", "description": "Initializes editing mode for a specific loyalty record."}, {"name": "save", "description": "Saves the updated loyalty data back to the API."}, {"name": "Loyalty()", "scope": "", "scopeKind": "", "description": "unavailable"}], "calls": ["api.get", "api.put", "setItems", "setLoading", "setEditing", "setForm", "useEffect", "alert", "load"], "search-terms": ["React Loyalty.jsx", "useState Loyalty component", "API loyalty management", "Loyalty account editing", "Loyalty data table"], "state": 2, "file_id": 20, "knowledge_revision": 48, "git_revision": "", "ctags": [{"_type": "tag", "name": "Loyalty", "path": "/home/kavia/workspace/code-generation/uppuveli-beach-mobile-application-19886-20862/WebAdminPanel/src/pages/Loyalty.jsx", "pattern": "/^export default function Loyalty() {$/", "language": "JavaScript", "kind": "function", "signature": "()"}], "hash": "c867ded34aa598ee33c2515f7be84b05", "format-version": 4, "code-base-name": "WebAdminPanel", "filename": "WebAdminPanel/src/pages/Loyalty.jsx", "revision_history": [{"48": ""}]}